Combinational/Addition and Subtraction/addsub.v
module addsub(
	input wire ctrl,
	input wire [3:0] a,
	input wire [3:0] b,
	output reg [3:0] z
);

always @(*)
begin
	if (ctrl)
	begin
		z=a+b;
	end

	else
		z=a-b;
end
endmodule

Combinational/Q26/addsub_tb.v
module addsub_tb;

reg ctrl;
reg [3:0] a;
reg [3:0] b;
wire [3:0] z;

addsub dut(
	.ctrl(ctrl),
	.a(a),
	.b(b),
	.z(z)
);

initial begin
	ctrl = 0;
	forever #10 ctrl = ~ctrl;
end
initial begin
	a=4'b0011;
	b=4'b1100;
	#20
	a=4'b1010;
	b=4'b0101;
	#20
	a=4'b1111;
	b=4'b0001;
	#20
	a=4'b0111;
	b=4'b0000;

	#10 $finish;
end

initial begin
	$dumpfile("addsub.vcd");
	$dumpvars(0,addsub);
end
endmodule

Combinational/Addition and Subtraction/addsub.vcd
$version Generated by VerilatedVcd $end
$timescale 1ps $end
 $scope module $rootio $end
 $upscope $end
 $scope module addsub_tb $end
  $var wire 1 # ctrl $end
  $var wire 4 $ a [3:0] $end
  $var wire 4 % b [3:0] $end
  $var wire 4 & z [3:0] $end
  $scope module dut $end
   $var wire 1 # ctrl $end
   $var wire 4 $ a [3:0] $end
   $var wire 4 % b [3:0] $end
   $var wire 4 & z [3:0] $end
  $upscope $end
 $upscope $end
$enddefinitions $end


#0
0#
b0011 $
b1100 %
b0111 &
#10
1#
b1111 &
#20
0#
b1010 $
b0101 %
b0101 &
#30
1#
b1111 &
#40
0#
b1111 $
b0001 %
b1110 &
#50
1#
b0000 &
#60
0#
b0111 $
b0000 %
b0111 &
#70
1#
