Sequential/Johnson Counter/jhc.v
module jhc(
	input wire clk,
	input wire reset,
	output reg [3:0] q
);

always @(posedge clk or posedge reset)
begin
	if (reset)
	begin
		q <= 4'b0;
	end

	else
		q <= {~q[0],q[3:1]};
end
endmodule

Sequential/Johnson Counter/jhc_tb.v
module jhc_tb;

reg clk;
reg reset;
wire [3:0] q;

jhc dut(
	.clk(clk),
	.reset(reset),
	.q(q)
);

initial begin
	clk = 0;
	forever #10 clk = ~clk;
end

initial begin
	
	$dumpfile("jhc.vcd");
	$dumpvars(0,jhc);

	reset = 1;
	#10;
	reset = 0;

	#500 $finish;
end
endmodule

Sequential/Johnson Counter/jhc.vcd
$version Generated by VerilatedVcd $end
$timescale 1ps $end
 $scope module $rootio $end
 $upscope $end
 $scope module jhc_tb $end
  $var wire 1 # clk $end
  $var wire 1 $ reset $end
  $var wire 4 % q [3:0] $end
  $scope module dut $end
   $var wire 1 # clk $end
   $var wire 1 $ reset $end
   $var wire 4 % q [3:0] $end
  $upscope $end
 $upscope $end
$enddefinitions $end


#0
0#
1$
b0000 %
#10
1#
0$
b1000 %
#20
0#
#30
1#
b1100 %
#40
0#
#50
1#
b1110 %
#60
0#
#70
1#
b1111 %
#80
0#
#90
1#
b0111 %
#100
0#
#110
1#
b0011 %
#120
0#
#130
1#
b0001 %
#140
0#
#150
1#
b0000 %
#160
0#
#170
1#
b1000 %
#180
0#
#190
1#
b1100 %
#200
0#
#210
1#
b1110 %
#220
0#
#230
1#
b1111 %
#240
0#
#250
1#
b0111 %
#260
0#
#270
1#
b0011 %
#280
0#
#290
1#
b0001 %
#300
0#
#310
1#
b0000 %
#320
0#
#330
1#
b1000 %
#340
0#
#350
1#
b1100 %
#360
0#
#370
1#
b1110 %
#380
0#
#390
1#
b1111 %
#400
0#
#410
1#
b0111 %
#420
0#
#430
1#
b0011 %
#440
0#
#450
1#
b0001 %
#460
0#
#470
1#
b0000 %
#480
0#
#490
1#
b1000 %
#500
0#
#510
1#
b1100 %
