Combinational/8x1demux/demux1x8.v
module demux1x8(
	input A,
	input [2:0] S,
	output wire [7:0] D);

assign D[0] = A & (S==3'b000);
assign D[1] = A & (S==3'b001);
assign D[2] = A & (S==3'b010);
assign D[3] = A & (S==3'b011);
assign D[4] = A & (S==3'b100);
assign D[5] = A & (S==3'b101);
assign D[6] = A & (S==3'b110);
assign D[7] = A & (S==3'b111);

endmodule

Combinational/8x1demux/demux1x8_tb.v
module demux1x8_tb;

reg A;
reg [2:0] S;
wire [7:0] D;

demux1x8 uut(
	.A(A),
	.D(D),
	.S(S)
);

initial begin


$monitor("Time=  %t,D= %b,A= %b,S= %b",$time,D,A,S);

A=0; S=3'b00;
#10 A=1; S=3'b000;
#10 S=3'b001;
#10 S=3'b010;
#10 S=3'b011;
#10 S=3'b100;
#10 S=3'b101;
#10 S=3'b110;
#10 S=3'b111;

#10 A=0; S=3'b000;
#10 $finish;
end

initial
begin
	$dumpfile("demux1x8.vcd");
	$dumpvars(0,demux1x8);
end
endmodule

Combinational/8x1demux/demux1x8.vcd
$version Generated by VerilatedVcd $end
$timescale 1ps $end
 $scope module $rootio $end
 $upscope $end
 $scope module demux1x8_tb $end
  $var wire 1 # A $end
  $var wire 3 $ S [2:0] $end
  $var wire 8 % D [7:0] $end
  $scope module uut $end
   $var wire 1 # A $end
   $var wire 3 $ S [2:0] $end
   $var wire 8 % D [7:0] $end
  $upscope $end
 $upscope $end
$enddefinitions $end


#0
0#
b000 $
b00000000 %
#10
1#
b00000001 %
#20
b001 $
b00000010 %
#30
b010 $
b00000100 %
#40
b011 $
b00001000 %
#50
b100 $
b00010000 %
#60
b101 $
b00100000 %
#70
b110 $
b01000000 %
#80
b111 $
b10000000 %
#90
0#
b000 $
b00000000 %
