Sequential/Gray Code Converter/grayc.v
module grayc(
	input wire clk,
	input wire reset,
	output reg [7:0] g
);

reg [7:0] b;
always @(posedge clk or posedge reset)
begin
	if (reset)
	begin
		g<=8'b0;
		b<=8'b0;
	end

	else
	begin
		b <= b+1;
		g <= (b >> 1)^b;
	end
end
endmodule

Sequential/Gray Code Converter/grayc_tb.v
module grayc_tb;

reg clk;
reg reset;
wire [7:0] g;

grayc dut(
	.clk(clk),
	.reset(reset),
	.g(g)
);

initial begin
	clk = 0;
	forever #10 clk=~clk;
end

initial begin
	reset = 1;
	#10
	reset = 0;

	#300 $finish;
end

initial begin 
	$dumpfile("grayc.vcd");
	$dumpvars(0,grayc);
end
endmodule

Sequential/Gray Code Converter/grayc.vcd
$version Generated by VerilatedVcd $end
$timescale 1ps $end
 $scope module $rootio $end
 $upscope $end
 $scope module grayc_tb $end
  $var wire 1 # clk $end
  $var wire 1 $ reset $end
  $var wire 8 % g [7:0] $end
  $scope module dut $end
   $var wire 1 # clk $end
   $var wire 1 $ reset $end
   $var wire 8 % g [7:0] $end
   $var wire 8 & b [7:0] $end
  $upscope $end
 $upscope $end
$enddefinitions $end


#0
0#
1$
b00000000 %
b00000000 &
#10
1#
0$
b00000001 &
#20
0#
#30
1#
b00000001 %
b00000010 &
#40
0#
#50
1#
b00000011 %
b00000011 &
#60
0#
#70
1#
b00000010 %
b00000100 &
#80
0#
#90
1#
b00000110 %
b00000101 &
#100
0#
#110
1#
b00000111 %
b00000110 &
#120
0#
#130
1#
b00000101 %
b00000111 &
#140
0#
#150
1#
b00000100 %
b00001000 &
#160
0#
#170
1#
b00001100 %
b00001001 &
#180
0#
#190
1#
b00001101 %
b00001010 &
#200
0#
#210
1#
b00001111 %
b00001011 &
#220
0#
#230
1#
b00001110 %
b00001100 &
#240
0#
#250
1#
b00001010 %
b00001101 &
#260
0#
#270
1#
b00001011 %
b00001110 &
#280
0#
#290
1#
b00001001 %
b00001111 &
#300
0#
#310
1#
b00001000 %
b00010000 &
