Combinational/Q23/disp.v
module disp(
	input wire [3:0] i,
	output reg [6:0] d
);

always @(*)
begin
	case (i)
		4'b0000: d=7'b1111110;
		4'b0001: d=7'b0110000;
		4'b0010: d=7'b1101101;
		4'b0011: d=7'b1111001;
		4'b0100: d=7'b0110011;
		4'b0101: d=7'b1011011;
		4'b0110: d=7'b1011111;
		4'b0111: d=7'b1110000;
		4'b1000: d=7'b1111111;
		4'b1001: d=7'b1111011;
		default: d=7'b0000000;
	endcase
end
endmodule

Combinational/Q23/disp_tb.v
module disp_tb;

reg [3:0] i;
wire [6:0] d;

disp dut(
	.i(i),
	.d(d)
);

initial begin
	i=4'b0000;
	#10 i=4'b1010;
	#10 i=4'b1110;
	#10 i=4'b1111;
	#10 i=4'b0001;
	#10 i=4'b0010;
	#10 i=4'b0011;
	#10 i=4'b0100;
	#10 i=4'b0101;
	#10 i=4'b0110;
	#10 i=4'b0111;
	#10 i=4'b1000;
	#10 i=4'b1001;

	#10 $finish;
end

initial begin
	$dumpfile("disp.vcd");
	$dumpvars(0,disp);
end
endmodule

Combinational/BCD to 7-Segment/disp.vcd
$version Generated by VerilatedVcd $end
$timescale 1ps $end
 $scope module $rootio $end
 $upscope $end
 $scope module disp_tb $end
  $var wire 4 # i [3:0] $end
  $var wire 7 $ d [6:0] $end
  $scope module dut $end
   $var wire 4 # i [3:0] $end
   $var wire 7 $ d [6:0] $end
  $upscope $end
 $upscope $end
$enddefinitions $end


#0
b0000 #
b1111110 $
#10
b1010 #
b0000000 $
#20
b1110 #
#30
b1111 #
#40
b0001 #
b0110000 $
#50
b0010 #
b1101101 $
#60
b0011 #
b1111001 $
#70
b0100 #
b0110011 $
#80
b0101 #
b1011011 $
#90
b0110 #
b1011111 $
#100
b0111 #
b1110000 $
#110
b1000 #
b1111111 $
#120
b1001 #
b1111011 $
