Sequential/Up-Down Counter/udc.v
module udc(
	input wire clk,
	input wire rst,
	input wire up,
	input wire down,
	output reg [3:0] c
);

always @(posedge clk or posedge rst)
begin
	if (rst)
	begin
		c <= 4'b0;
	end
	else 
	begin
		if (up)
		begin
			c <= c+1;
		end
		else if (down)
		begin
			c <= c-1;
		end
		else
			c <= c;
	end
end
endmodule

Sequential/Up-Down Counter/udc_tb.v
module udc_tb;

reg clk,rst,up,down;
reg [3:0] c;

udc dut(
	.clk(clk),
	.rst(rst),
	.up(up),
	.down(down),
	.c(c)
);

initial begin
	rst = 1;
	#10 rst = 0;
	c = 4'b1100;
	#300 $finish;
end

initial begin
	clk = 0;
	forever #10 clk = ~clk;
end

initial begin
	up = 0;
	#10 up =1;
	#50 up =0;
end

initial begin
	down = 0;
	#100 down = 1;
	#100 down = 0;
end

initial begin
	$monitor("Time=  %t,Up=  %b,Down=  %b",$time,up,down);
end

initial begin
	$dumpfile("udc.vcd");
	$dumpvars(0,udc);
end
endmodule

Sequential/Up-Down Counter/udc.vcd
$version Generated by VerilatedVcd $end
$timescale 1ps $end
 $scope module $rootio $end
 $upscope $end
 $scope module udc_tb $end
  $var wire 1 # clk $end
  $var wire 1 $ rst $end
  $var wire 1 % up $end
  $var wire 1 & down $end
  $var wire 4 ' c [3:0] $end
  $scope module dut $end
   $var wire 1 # clk $end
   $var wire 1 $ rst $end
   $var wire 1 % up $end
   $var wire 1 & down $end
   $var wire 4 ' c [3:0] $end
  $upscope $end
 $upscope $end
$enddefinitions $end


#0
0#
1$
0%
0&
b0000 '
#10
1#
0$
1%
b1101 '
#20
0#
#30
1#
b1110 '
#40
0#
#50
1#
b1111 '
#60
0#
0%
#70
1#
#80
0#
#90
1#
#100
0#
1&
#110
1#
b1110 '
#120
0#
#130
1#
b1101 '
#140
0#
#150
1#
b1100 '
#160
0#
#170
1#
b1011 '
#180
0#
#190
1#
b1010 '
#200
0#
0&
