Sequential/Ring Counter/rcounter.v
module rcounter(
	input wire clk,
	input wire reset,
	input wire enable,
	output reg [3:0] q
);

always @(posedge clk or posedge reset)
begin
	if (reset)
	begin
		q<=4'b0;
	end
	else
	begin
		if (enable)
		begin
			q<=q+1;
		end
		else
			q<=q;
	end
end
endmodule

Sequential/Ring Counter/rcounter_tb.v
module rcounter_tb;

reg clk;
reg reset;
reg enable;
wire [3:0] q;

rcounter dut(
	.clk(clk),
	.reset(reset),
	.enable(enable),
	.q(q)
);

initial begin
	clk = 0;
	forever #10 clk=~clk;
end

initial begin
	reset = 1;
	enable = 1;
	#10 reset = 0;
	#50 enable = 0;
	#20 enable = 1;

	#50 $finish;
end

initial begin
	$dumpfile("rcounter.vcd");
	$dumpvars(0,rcounter);
end
endmodule

Sequential/Ring Counter/rcounter.vcd
$version Generated by VerilatedVcd $end
$timescale 1ps $end
 $scope module $rootio $end
 $upscope $end
 $scope module rcounter_tb $end
  $var wire 1 # clk $end
  $var wire 1 $ reset $end
  $var wire 1 % enable $end
  $var wire 4 & q [3:0] $end
  $scope module dut $end
   $var wire 1 # clk $end
   $var wire 1 $ reset $end
   $var wire 1 % enable $end
   $var wire 4 & q [3:0] $end
  $upscope $end
 $upscope $end
$enddefinitions $end


#0
0#
1$
1%
b0000 &
#10
1#
0$
b0001 &
#20
0#
#30
1#
b0010 &
#40
0#
#50
1#
b0011 &
#60
0#
0%
#70
1#
#80
0#
1%
#90
1#
b0100 &
#100
0#
#110
1#
b0101 &
#120
0#
#130
1#
b0110 &
