Combinational/Priority Encoder/pencoder.v
module pencoder(
	input wire [7:0] d,
	output reg [2:0] o
);

always @(*)
begin
	if (d[0])
	begin
		o = 3'b0;
	end
	else if (d[1])
	begin
		o = 3'b001;
	end
	else if (d[2])
	begin
		o = 3'b010;
	end
	else if (d[3])
	begin
		o = 3'b011;
	end
	else if (d[4])
	begin
		o = 3'b100;
	end
	else if (d[5])
	begin
		o = 3'b101;
	end
	else if (d[6])
	begin
		o = 3'b110;
	end
	else if (d[7])
	begin
		o = 3'b111;
	end
	else
		o = 3'b0;
end
endmodule

Combinational/Priority Encoder/pencoder_tb.v
module pencoder_tb;

reg [7:0] d;
wire [2:0] o;

pencoder dut(
	.d(d),
	.o(o)
);

initial begin
	d = 8'b11111111;
	#10 d = 8'b10000000;
	#10 d = 8'b01111111;
	#10 d = 8'b01000000;
	#10 d = 8'b00111111;
	#10 d = 8'b00100000;
	#10 d = 8'b00011111;
	#10 d = 8'b00010000;
	#10 d = 8'b00001111;
	#10 d = 8'b00001000;
	#10 d = 8'b00000111;
	#10 d = 8'b00000100;
	#10 d = 8'b00000011;
	#10 d = 8'b00000010;
	#10 d = 8'b00000001;

	#10 $finish;
end

initial begin
	$dumpfile("pencoder.vcd");
	$dumpvars(0,pencoder);
end
endmodule

Combinational/Q22/pencoder.vcd
$version Generated by VerilatedVcd $end
$timescale 1ps $end
 $scope module $rootio $end
 $upscope $end
 $scope module pencoder_tb $end
  $var wire 8 # d [7:0] $end
  $var wire 3 $ o [2:0] $end
  $scope module dut $end
   $var wire 8 # d [7:0] $end
   $var wire 3 $ o [2:0] $end
  $upscope $end
 $upscope $end
$enddefinitions $end


#0
b11111111 #
b000 $
#10
b10000000 #
b111 $
#20
b01111111 #
b000 $
#30
b01000000 #
b110 $
#40
b00111111 #
b000 $
#50
b00100000 #
b101 $
#60
b00011111 #
b000 $
#70
b00010000 #
b100 $
#80
b00001111 #
b000 $
#90
b00001000 #
b011 $
#100
b00000111 #
b000 $
#110
b00000100 #
b010 $
#120
b00000011 #
b000 $
#130
b00000010 #
b001 $
#140
b00000001 #
b000 $
