Combinational/mux8x1/mux8x1.v
module mux8x1(
	input [7:0] D,
input [2:0] S,
output Z
);

assign Z= (S==3'b000) ? D[7]:
	(S==3'b001)?D[6]:
	(S==3'b010)?D[5]:
	(S==3'b011)?D[4]:
	(S==3'b100)?D[3]:
	(S==3'b101)?D[2]:
	(S==3'b110)?D[1]:
	D[0];
endmodule

Combinational/mux8x1/mux8x1_tb.v
module mux8x1_tb;
reg [7:0] D;
reg [2:0] S;
wire Z;

mux8x1 uut(
.D(D),
.S(S),
.Z(Z)
);

initial begin
	D=8'b00000000;
	S=3'b000;

	$display("TEST CASE|S|D|Z");
	$monitor("	%b	%b	%b",S,D,Z);

	#10 D=8'b10000000; S=3'b000;
	#10 D=8'b01000000; S=3'b000;
	#10 D=8'b00100000; S=3'b010;
	#10 D=8'b00010000; S=3'b011;
	#10 D=8'b00001000; S=3'b100;
	#10 D=8'b00000100; S=3'b101;
	#10 D=8'b00000010; S=3'b110;
	#10 D=8'b00000001; S=3'b111;
	#10 $finish;
end
initial
begin
	$dumpfile("mux8x1.vcd");
	$dumpvars(0,mux8x1);
end
endmodule

Combinational/mux8x1/mux8x1.vcd
$version Generated by VerilatedVcd $end
$timescale 1ps $end
 $scope module $rootio $end
 $upscope $end
 $scope module mux8x1_tb $end
  $var wire 8 # D [7:0] $end
  $var wire 3 $ S [2:0] $end
  $var wire 1 % Z $end
  $scope module uut $end
   $var wire 8 # D [7:0] $end
   $var wire 3 $ S [2:0] $end
   $var wire 1 % Z $end
  $upscope $end
 $upscope $end
$enddefinitions $end


#0
b00000000 #
b000 $
0%
#10
b10000000 #
1%
#20
b01000000 #
0%
#30
b00100000 #
b010 $
1%
#40
b00010000 #
b011 $
#50
b00001000 #
b100 $
#60
b00000100 #
b101 $
#70
b00000010 #
b110 $
#80
b00000001 #
b111 $
