Combinational/Q3/cequ_ops.v
module cequ_ops(
	input wire [3:0] a,
	input wire [3:0] b,
	output reg z
);

always @(*)
begin
	if (a === b)
	begin
		z = 1;
	end
	else
	begin
		z = 0;
	end
end
endmodule

Combinational/Q3/cequ_ops_tb.v
module cequ_ops_tb;

reg [3:0] a,b;
wire z;

cequ_ops dut(
	.a(a),
	.b(b),
	.z(z)
);

initial begin
	a = 4'b0;
	#10 a = 4'b1x0z;
	b = 4'b0;
	#5 b = 4'b1x0z;
	#100 $finish;
end

initial begin
	forever #10 a = ~a;
end

initial begin
	$dumpfile("cequ_ops.vcd");
	$dumpvars(0,cequ_ops);
end
endmodule

Combinational/Q3/cequ_ops.vcd
$version Generated by VerilatedVcd $end
$timescale 1ps $end
 $scope module $rootio $end
 $upscope $end
 $scope module cequ_ops_tb $end
  $var wire 4 # a [3:0] $end
  $var wire 4 $ b [3:0] $end
  $var wire 1 % z $end
  $scope module dut $end
   $var wire 4 # a [3:0] $end
   $var wire 4 $ b [3:0] $end
   $var wire 1 % z $end
  $upscope $end
 $upscope $end
$enddefinitions $end


#0
b0000 #
b0000 $
1%
#10
b1111 #
0%
#15
b1000 $
#20
b1000 #
1%
#30
b1111 #
0%
#40
b1000 #
1%
#50
b1111 #
0%
#60
b1000 #
1%
#70
b1111 #
0%
#80
b1000 #
1%
#90
b1111 #
0%
#100
b1000 #
1%
#110
b1111 #
0%
