Combinational/4:2_Encoder/encoder4x2.v
module encoder4x2(
	input wire [3:0] A,
	output reg [1:0] Z);

always @(*)
	case(A)
		4'b0001: Z = 2'b00;
		4'b0010: Z = 2'b01;
		4'b0100: Z = 2'b10;
		4'b1000: Z = 2'b11;
		default: Z = 2'bxx;
	endcase

endmodule

Combinational/4:2_Encoder/encoder4x2_tb.v
module encoder4x2_tb;

reg [3:0] A;
wire [1:0] Z;

encoder4x2 dut(
	.A(A),
	.Z(Z)
);

initial begin
$monitor("Time= %t,A= %b,Z= %b",$time,A,Z);

#10 A=4'b0001;
#10 A=4'b1110;
#10 A=4'b0010;
#10 A=4'b1101;
#10 A=4'b0100;
#10 A=4'b1011;
#10 A=4'b1000;
#10 A=4'b0111;

#10 $finish;
end

initial
begin
	$dumpfile("encoder4x2.vcd");
	$dumpvars(0,encoder4x2);
end
endmodule

Combinational/4:2_Encoder/encoder4x2.vcd
$version Generated by VerilatedVcd $end
$timescale 1ps $end
 $scope module $rootio $end
 $upscope $end
 $scope module encoder4x2_tb $end
  $var wire 4 # A [3:0] $end
  $var wire 2 $ Z [1:0] $end
  $scope module dut $end
   $var wire 4 # A [3:0] $end
   $var wire 2 $ Z [1:0] $end
  $upscope $end
 $upscope $end
$enddefinitions $end


#0
b0000 #
b00 $
#10
b0001 #
#20
b1110 #
#30
b0010 #
b01 $
#40
b1101 #
b00 $
#50
b0100 #
b10 $
#60
b1011 #
b00 $
#70
b1000 #
b11 $
#80
b0111 #
b00 $
