Sequential/Decade Counter/dec_count.v
module dec_count(
	input wire clk,
	input wire rst,
	output reg [3:0] c
);

always @(posedge clk or posedge rst)
begin
	if (rst) begin
		c <= 4'b000;
	end
	else if (c == 4'b1001) begin
		c <= 4'b000;
	end
	else begin
		c <= c+1;
	end
end
endmodule

Sequential/Decade Counter/dec_count_tb.v
module dec_count_tb;

reg clk;
reg rst;
wire [3:0] c;

dec_count dut(
	.clk(clk),
	.rst(rst),
	.c(c)
);

initial begin
	clk = 0;
	forever #5 clk = ~clk;
end

initial begin
	rst = 1;
	#10 rst = 0;
	#100 $finish;
end

initial begin
	$monitor("Time=  %t,Reset=  %b",$time,rst);
end
initial begin
	$dumpfile("dec_count.vcd");
	$dumpvars(0,dec_count);
end
endmodule

Sequential/Decade Counter/dec_count.vcd
$version Generated by VerilatedVcd $end
$timescale 1ps $end
 $scope module $rootio $end
 $upscope $end
 $scope module dec_count_tb $end
  $var wire 1 # clk $end
  $var wire 1 $ rst $end
  $var wire 4 % c [3:0] $end
  $scope module dut $end
   $var wire 1 # clk $end
   $var wire 1 $ rst $end
   $var wire 4 % c [3:0] $end
  $upscope $end
 $upscope $end
$enddefinitions $end


#0
0#
1$
b0000 %
#5
1#
#10
0#
0$
#15
1#
b0001 %
#20
0#
#25
1#
b0010 %
#30
0#
#35
1#
b0011 %
#40
0#
#45
1#
b0100 %
#50
0#
#55
1#
b0101 %
#60
0#
#65
1#
b0110 %
#70
0#
#75
1#
b0111 %
#80
0#
#85
1#
b1000 %
#90
0#
#95
1#
b1001 %
#100
0#
#105
1#
b0000 %
