Combinational/4x1mux/mux4x1.v
module mux4x1(D0,D1,D2,D3,S1,S2,Z);
input D0,D1,D2,D3,S1,S2;
output Z;
reg Z;

assign Z= (S1==0 && S2==0)?D0:
	(S1==0&&S2==1)?D1:
	(S1==1&&S2==0)?D2:
	D3;
endmodule

Combinational/4x1mux/mux_tb.v
module mux_tb;
reg D0,D1,D2,D3;
reg S1,S2;
wire Z;

mux4x1 uut(
	.D0(D0),
	.D1(D1),
	.D2(D2),
	.D3(D3),
	.S1(S1),
	.S2(S2),
	.Z(Z)
);

initial begin
	D0=0;D1=0;D2=0;D3=0;
	S1=0;S2=0;

	$display("Test Case|S1 S2|D0 D1 D2 D3|Z");
	$monitor("	%b %b   %b %b %b %b|%b",S1,S2,D0,D1,D2,D3,Z);

	#10 D0=1;D1=0;D2=0;D3=0;S1=0;S2=0;
	#10 D0=0;D1=1;D2=0;D3=0;S1=0;S2=1;
	#10 D0=0;D1=0;D2=1;D3=0;S1=1;S2=0;
	#10 D0=0;D1=0;D2=0;D3=1;S1=1;S2=1;
	#10 D0=0;D1=1;D2=1;D3=1;S1=0;S2=0;
	#10 D0=1;D1=0;D2=1;D3=1;S1=0;S2=1;
	#10 D0=1;D1=1;D2=0;D3=1;S1=1;S2=0;
	#10 D0=1;D1=1;D2=1;D3=0;S1=1;S2=1;
end
initial
begin
	$dumpfile("mux4x1.vcd");
	$dumpvars(0,mux);
end
endmodule

Combinational/4x1mux/mux4x1.vcd
$version Generated by VerilatedVcd $end
$timescale 1ps $end
 $scope module $rootio $end
 $upscope $end
 $scope module mux_tb $end
  $var wire 1 # D0 $end
  $var wire 1 $ D1 $end
  $var wire 1 % D2 $end
  $var wire 1 & D3 $end
  $var wire 1 ' S1 $end
  $var wire 1 ( S2 $end
  $var wire 1 ) Z $end
  $scope module uut $end
   $var wire 1 # D0 $end
   $var wire 1 $ D1 $end
   $var wire 1 % D2 $end
   $var wire 1 & D3 $end
   $var wire 1 ' S1 $end
   $var wire 1 ( S2 $end
   $var wire 1 ) Z $end
  $upscope $end
 $upscope $end
$enddefinitions $end


#0
0#
0$
0%
0&
0'
0(
0)
#10
1#
1)
#20
0#
1$
1(
#30
0$
1%
1'
0(
#40
0%
1&
1(
#50
1$
1%
0'
0(
0)
#60
1#
0$
1(
#70
1$
0%
1'
0(
#80
1%
0&
1(
