Combinational/Q2/equ_ops.v
module equ_ops(
	input wire [3:0] a,
	input wire [3:0] b,
	output reg  z
);

always @(*)
begin
	if (a == b)
	begin
		z = 1;
	end
	else
		z = 0;
end
endmodule

Combinational/Q2/equ_ops_tb.v
module equ_ops_tb;

reg [3:0] a;
reg [3:0] b;
wire z;

equ_ops dut(
	.a(a),
	.b(b),
	.z(z)
);

initial begin
	a = 0;
	b = 0;
	#10 a = 4'b10x1;
	#5 b = 4'b10x1;
	#100 $finish;
end

initial begin
	forever #10 a = ~a;
end

initial begin
	$dumpfile("equ_ops.vcd");
	$dumpvars(0,equ_ops);
end
endmodule

Combinational/Q2/equ_ops.vcd
$version Generated by VerilatedVcd $end
$timescale 1ps $end
 $scope module $rootio $end
 $upscope $end
 $scope module equ_ops_tb $end
  $var wire 4 # a [3:0] $end
  $var wire 4 $ b [3:0] $end
  $var wire 1 % z $end
  $scope module dut $end
   $var wire 4 # a [3:0] $end
   $var wire 4 $ b [3:0] $end
   $var wire 1 % z $end
  $upscope $end
 $upscope $end
$enddefinitions $end


#0
b0000 #
b0000 $
1%
#10
b0110 #
0%
#15
b1001 $
#20
b1001 #
1%
#30
b0110 #
0%
#40
b1001 #
1%
#50
b0110 #
0%
#60
b1001 #
1%
#70
b0110 #
0%
#80
b1001 #
1%
#90
b0110 #
0%
#100
b1001 #
1%
#110
b0110 #
0%
